snipkit/VERSION.txt
snipkit/__init__.py
snipkit/__main__.py
snipkit/cli.py
snipkit/config.py
snipkit/environment.py
snipkit/exceptions.py
snipkit/extensions.py
snipkit/find.py
snipkit/generate.py
snipkit/hooks.py
snipkit/log.py
snipkit/main.py
snipkit/prompt.py
snipkit/replay.py
snipkit/repository.py
snipkit/utils.py
snipkit/vcs.py
snipkit/zipfile.py
snipkit-1.0.0.dist-info/licenses/LICENSE
snipkit-1.0.0.dist-info/METADATA
snipkit-1.0.0.dist-info/WHEEL
snipkit-1.0.0.dist-info/entry_points.txt
snipkit-1.0.0.dist-info/top_level.txt
snipkit-1.0.0.dist-info/RECORD
