Metadata-Version: 2.4
Name: snipkit
Version: 1.0.0
Summary: A command-line utility that creates projects from project templates, e.g. creating a Python package project from a Python package project template.
Home-page: https://github.com/khulnasoft/snipkit
Author: Md Sulaiman
Author-email: dev.sulaiman@icloud.com
License: BSD
Project-URL: Documentation, https://snipkit.readthedocs.io
Project-URL: Issues, https://github.com/khulnasoft/snipkit/issues
Keywords: snipkit,Python,projects,project templates,Jinja2,skeleton,scaffolding,project directory,package,packaging
Classifier: Development Status :: 5 - Production/Stable
Classifier: Environment :: Console
Classifier: Intended Audience :: Developers
Classifier: Natural Language :: English
Classifier: License :: OSI Approved :: BSD License
Classifier: Programming Language :: Python :: 3 :: Only
Classifier: Programming Language :: Python :: 3
Classifier: Programming Language :: Python :: 3.8
Classifier: Programming Language :: Python :: 3.9
Classifier: Programming Language :: Python :: 3.10
Classifier: Programming Language :: Python :: 3.11
Classifier: Programming Language :: Python :: 3.12
Classifier: Programming Language :: Python :: Implementation :: CPython
Classifier: Programming Language :: Python :: Implementation :: PyPy
Classifier: Programming Language :: Python
Classifier: Topic :: Software Development
Requires-Python: >=3.8
License-File: LICENSE
Requires-Dist: binaryornot>=0.4.4
Requires-Dist: Jinja2<4.0.0,>=2.7
Requires-Dist: click<9.0.0,>=7.0
Requires-Dist: pyyaml>=5.3.1
Requires-Dist: python-slugify>=4.0.0
Requires-Dist: requests>=2.23.0
Requires-Dist: arrow
Requires-Dist: rich
Dynamic: author
Dynamic: author-email
Dynamic: classifier
Dynamic: description
Dynamic: description-content-type
Dynamic: home-page
Dynamic: keywords
Dynamic: license
Dynamic: license-file
Dynamic: project-url
Dynamic: requires-dist
Dynamic: requires-python
Dynamic: summary
